swiftonpython/__init__.py
swiftonpython/main.swift
swiftonpython/swift.py
swiftonpython-0.8.dist-info/METADATA
swiftonpython-0.8.dist-info/WHEEL
swiftonpython-0.8.dist-info/top_level.txt
swiftonpython-0.8.dist-info/RECORD
