Metadata-Version: 2.1
Name: swiftonpython
Version: 0.8
Summary: A Python library to run Swift code
Home-page: https://github.com/bobbyshop-vui/swiftonpython
Author: Bobby
License: UNKNOWN
Platform: UNKNOWN
